odoo/addons/account_invoice_bank_details/README.rst
odoo/addons/account_invoice_bank_details/__init__.py
odoo/addons/account_invoice_bank_details/__manifest__.py
odoo/addons/account_invoice_bank_details/i18n/account_invoice_bank_details.pot
odoo/addons/account_invoice_bank_details/i18n/fr.po
odoo/addons/account_invoice_bank_details/i18n/it.po
odoo/addons/account_invoice_bank_details/models/__init__.py
odoo/addons/account_invoice_bank_details/models/account_move.py
odoo/addons/account_invoice_bank_details/readme/CONTRIBUTORS.md
odoo/addons/account_invoice_bank_details/readme/CREDITS.md
odoo/addons/account_invoice_bank_details/readme/DESCRIPTION.md
odoo/addons/account_invoice_bank_details/report/invoice_report_templates.xml
odoo/addons/account_invoice_bank_details/static/description/icon.png
odoo/addons/account_invoice_bank_details/static/description/index.html
odoo_addon_account_invoice_bank_details-17.0.1.0.1.dist-info/METADATA
odoo_addon_account_invoice_bank_details-17.0.1.0.1.dist-info/WHEEL
odoo_addon_account_invoice_bank_details-17.0.1.0.1.dist-info/top_level.txt
odoo_addon_account_invoice_bank_details-17.0.1.0.1.dist-info/RECORD
