Metadata-Version: 2.1
Name: odoo-addon-account_invoice_bank_details
Version: 17.0.1.0.1
Requires-Python: >=3.10
Requires-Dist: odoo>=17.0a,<17.1dev
Summary: Select bank account base on currency + print bank details on reportreports and customer portal
Home-page: https://github.com/OCA/account-invoice-reporting
License: AGPL-3
Author: Camptocamp, Odoo Community Association (OCA)
Author-email: support@odoo-community.org
Classifier: Programming Language :: Python
Classifier: Framework :: Odoo
Classifier: Framework :: Odoo :: 17.0
Classifier: License :: OSI Approved :: GNU Affero General Public License v3
